unitrad/__init__.py
unitrad/unitrad.py
unitrad-0.1.0.dist-info/METADATA
unitrad-0.1.0.dist-info/WHEEL
unitrad-0.1.0.dist-info/entry_points.txt
unitrad-0.1.0.dist-info/top_level.txt
unitrad-0.1.0.dist-info/RECORD
