Metadata-Version: 2.1
Name: unitrad
Version: 0.1.0
Summary: A WebSocket client for trading strategies
Author: niexuan
Author-email: 18595847674@163.com
Requires-Dist: aiohttp
Requires-Dist: PyYAML
